decay_tools/__init__.py
decay_tools/fit.py
decay_tools/visualize.py
decay_tools-0.2.0.dist-info/METADATA
decay_tools-0.2.0.dist-info/WHEEL
decay_tools-0.2.0.dist-info/licenses/LICENSE
decay_tools-0.2.0.dist-info/RECORD
