Metadata-Version: 2.4
Name: decay-tools
Version: 0.2.0
Summary: Python package for fitting single- and double-component nuclear decay time distributions and estimating optimal bins in the logarithmic form.
Project-URL: Homepage, https://github.com/flnr-shels-dsp/decay-tools/
Project-URL: Issues, https://github.com/flnr-shels-dsp/decay-tools//issues
Project-URL: Changelog, https://github.com/flnr-shels-dsp/decay-tools/blob/main/CHANGELOG.md
Author: Andrey Isaev
Author-email: Roman Mukhin <rmukhin@jinr.ru>
License-Expression: MIT
License-File: LICENSE
Classifier: Operating System :: OS Independent
Classifier: Programming Language :: Python :: 3
Requires-Python: >=3.10
Requires-Dist: matplotlib>=3.10.1
Requires-Dist: numpy>=2.2.5
Requires-Dist: scipy>=1.15.2
